odoo8_addon_hr_phone-8.0.0.1.0.99.dev10-py2.7-nspkg.pth
odoo8_addon_hr_phone-8.0.0.1.0.99.dev10.dist-info/METADATA
odoo8_addon_hr_phone-8.0.0.1.0.99.dev10.dist-info/RECORD
odoo8_addon_hr_phone-8.0.0.1.0.99.dev10.dist-info/WHEEL
odoo8_addon_hr_phone-8.0.0.1.0.99.dev10.dist-info/namespace_packages.txt
odoo8_addon_hr_phone-8.0.0.1.0.99.dev10.dist-info/top_level.txt
odoo_addons/hr_phone/__init__.py
odoo_addons/hr_phone/__openerp__.py
odoo_addons/hr_phone/hr_phone.py
odoo_addons/hr_phone/hr_view.xml
odoo_addons/hr_phone/i18n/de.po
odoo_addons/hr_phone/i18n/es.po
odoo_addons/hr_phone/i18n/fr.po
odoo_addons/hr_phone/i18n/hr_phone.pot
odoo_addons/hr_phone/i18n/nl.po
odoo_addons/hr_phone/i18n/nl_NL.po
odoo_addons/hr_phone/i18n/sl.po
odoo_addons/hr_phone/i18n/tr.po
odoo_addons/hr_phone/i18n/zh_CN.po
odoo_addons/hr_phone/security/ir.model.access.csv
odoo_addons/hr_phone/static/description/icon.png
